num_system
