Metadata-Version: 2.1
Name: num-system
Version: 0.0.2
Summary: Перевод числа а в с.с. б из с.с. с
Home-page: https://github.com/TFL-group/num_sys
Author: Dimitry K
Author-email: dime_kozlov@mail.ru
License: MIT
Keywords: sis
